{"nodes": [{"id": "sources_qetversion_h", "label": "qetversion.h", "file_type": "code", "source_file": "sources/qetversion.h", "source_location": "L1"}, {"id": "qetversion_qetversion", "label": "QetVersion()", "file_type": "code", "source_file": "sources/qetversion.h", "source_location": "L24"}], "edges": [{"source": "sources_qetversion_h", "target": "qversionnumber", "relation": "imports", "confidence": "EXTRACTED", "source_file": "sources/qetversion.h", "source_location": "L21", "weight": 1.0}, {"source": "sources_qetversion_h", "target": "qdomelement", "relation": "imports", "confidence": "EXTRACTED", "source_file": "sources/qetversion.h", "source_location": "L22", "weight": 1.0}, {"source": "sources_qetversion_h", "target": "qetversion_qetversion", "relation": "contains", "confidence": "EXTRACTED", "source_file": "sources/qetversion.h", "source_location": "L24", "weight": 1.0}], "raw_calls": []}