{"nodes": [{"id": "sources_conductornumexport_cpp", "label": "conductornumexport.cpp", "file_type": "code", "source_file": "sources/conductornumexport.cpp", "source_location": "L1"}, {"id": "conductornumexport_conductornumexport", "label": "ConductorNumExport()", "file_type": "code", "source_file": "sources/conductornumexport.cpp", "source_location": "L35"}, {"id": "conductornumexport_tocsv", "label": "toCsv()", "file_type": "code", "source_file": "sources/conductornumexport.cpp", "source_location": "L47"}, {"id": "conductornumexport_wiresnum", "label": "wiresNum()", "file_type": "code", "source_file": "sources/conductornumexport.cpp", "source_location": "L99"}, {"id": "conductornumexport_fillhash", "label": "fillHash()", "file_type": "code", "source_file": "sources/conductornumexport.cpp", "source_location": "L119"}], "edges": [{"source": "sources_conductornumexport_cpp", "target": "conductornumexport", "relation": "imports", "confidence": "EXTRACTED", "source_file": "sources/conductornumexport.cpp", "source_location": "L18", "weight": 1.0}, {"source": "sources_conductornumexport_cpp", "target": "qetapp", "relation": "imports", "confidence": "EXTRACTED", "source_file": "sources/conductornumexport.cpp", "source_location": "L20", "weight": 1.0}, {"source": "sources_conductornumexport_cpp", "target": "diagram", "relation": "imports", "confidence": "EXTRACTED", "source_file": "sources/conductornumexport.cpp", "source_location": "L21", "weight": 1.0}, {"source": "sources_conductornumexport_cpp", "target": "diagramcontent", "relation": "imports", "confidence": "EXTRACTED", "source_file": "sources/conductornumexport.cpp", "source_location": "L22", "weight": 1.0}, {"source": "sources_conductornumexport_cpp", "target": "conductor", "relation": "imports", "confidence": "EXTRACTED", "source_file": "sources/conductornumexport.cpp", "source_location": "L23", "weight": 1.0}, {"source": "sources_conductornumexport_cpp", "target": "conductortextitem", "relation": "imports", "confidence": "EXTRACTED", "source_file": "sources/conductornumexport.cpp", "source_location": "L24", "weight": 1.0}, {"source": "sources_conductornumexport_cpp", "target": "element", "relation": "imports", "confidence": "EXTRACTED", "source_file": "sources/conductornumexport.cpp", "source_location": "L25", "weight": 1.0}, {"source": "sources_conductornumexport_cpp", "target": "terminal", "relation": "imports", "confidence": "EXTRACTED", "source_file": "sources/conductornumexport.cpp", "source_location": "L26", "weight": 1.0}, {"source": "sources_conductornumexport_cpp", "target": "qfiledialog", "relation": "imports", "confidence": "EXTRACTED", "source_file": "sources/conductornumexport.cpp", "source_location": "L28", "weight": 1.0}, {"source": "sources_conductornumexport_cpp", "target": "conductornumexport_conductornumexport", "relation": "contains", "confidence": "EXTRACTED", "source_file": "sources/conductornumexport.cpp", "source_location": "L35", "weight": 1.0}, {"source": "sources_conductornumexport_cpp", "target": "conductornumexport_tocsv", "relation": "contains", "confidence": "EXTRACTED", "source_file": "sources/conductornumexport.cpp", "source_location": "L47", "weight": 1.0}, {"source": "sources_conductornumexport_cpp", "target": "conductornumexport_wiresnum", "relation": "contains", "confidence": "EXTRACTED", "source_file": "sources/conductornumexport.cpp", "source_location": "L99", "weight": 1.0}, {"source": "sources_conductornumexport_cpp", "target": "conductornumexport_fillhash", "relation": "contains", "confidence": "EXTRACTED", "source_file": "sources/conductornumexport.cpp", "source_location": "L119", "weight": 1.0}, {"source": "conductornumexport_conductornumexport", "target": "conductornumexport_fillhash", "relation": "calls", "confidence": "EXTRACTED", "source_file": "sources/conductornumexport.cpp", "source_location": "L39", "weight": 1.0}, {"source": "conductornumexport_tocsv", "target": "conductornumexport_wiresnum", "relation": "calls", "confidence": "EXTRACTED", "source_file": "sources/conductornumexport.cpp", "source_location": "L76", "weight": 1.0}], "raw_calls": [{"caller_nid": "conductornumexport_tocsv", "callee": "currentDir", "source_file": "sources/conductornumexport.cpp", "source_location": "L50"}, {"caller_nid": "conductornumexport_tocsv", "callee": "isEmpty", "source_file": "sources/conductornumexport.cpp", "source_location": "L51"}, {"caller_nid": "conductornumexport_tocsv", "callee": "documentDir", "source_file": "sources/conductornumexport.cpp", "source_location": "L51"}, {"caller_nid": "conductornumexport_tocsv", "callee": "tr", "source_file": "sources/conductornumexport.cpp", "source_location": "L52"}, {"caller_nid": "conductornumexport_tocsv", "callee": "title", "source_file": "sources/conductornumexport.cpp", "source_location": "L52"}, {"caller_nid": "conductornumexport_tocsv", "callee": "getSaveFileName", "source_file": "sources/conductornumexport.cpp", "source_location": "L57"}, {"caller_nid": "conductornumexport_tocsv", "callee": "tr", "source_file": "sources/conductornumexport.cpp", "source_location": "L57"}, {"caller_nid": "conductornumexport_tocsv", "callee": "tr", "source_file": "sources/conductornumexport.cpp", "source_location": "L57"}, {"caller_nid": "conductornumexport_tocsv", "callee": "isEmpty", "source_file": "sources/conductornumexport.cpp", "source_location": "L59"}, {"caller_nid": "conductornumexport_tocsv", "callee": "exists", "source_file": "sources/conductornumexport.cpp", "source_location": "L61"}, {"caller_nid": "conductornumexport_tocsv", "callee": "remove", "source_file": "sources/conductornumexport.cpp", "source_location": "L64"}, {"caller_nid": "conductornumexport_tocsv", "callee": "critical", "source_file": "sources/conductornumexport.cpp", "source_location": "L66"}, {"caller_nid": "conductornumexport_tocsv", "callee": "tr", "source_file": "sources/conductornumexport.cpp", "source_location": "L66"}, {"caller_nid": "conductornumexport_tocsv", "callee": "tr", "source_file": "sources/conductornumexport.cpp", "source_location": "L67"}, {"caller_nid": "conductornumexport_tocsv", "callee": "open", "source_file": "sources/conductornumexport.cpp", "source_location": "L72"}, {"caller_nid": "conductornumexport_tocsv", "callee": "QT_VERSION_CHECK", "source_file": "sources/conductornumexport.cpp", "source_location": "L75"}, {"caller_nid": "conductornumexport_tocsv", "callee": "endl", "source_file": "sources/conductornumexport.cpp", "source_location": "L81"}, {"caller_nid": "conductornumexport_wiresnum", "callee": "keys", "source_file": "sources/conductornumexport.cpp", "source_location": "L103"}, {"caller_nid": "conductornumexport_wiresnum", "callee": "sort", "source_file": "sources/conductornumexport.cpp", "source_location": "L104"}, {"caller_nid": "conductornumexport_wiresnum", "callee": "value", "source_file": "sources/conductornumexport.cpp", "source_location": "L107"}, {"caller_nid": "conductornumexport_wiresnum", "callee": "append", "source_file": "sources/conductornumexport.cpp", "source_location": "L108"}, {"caller_nid": "conductornumexport_fillhash", "callee": "diagrams", "source_file": "sources/conductornumexport.cpp", "source_location": "L123"}, {"caller_nid": "conductornumexport_fillhash", "callee": "conductors", "source_file": "sources/conductornumexport.cpp", "source_location": "L126"}, {"caller_nid": "conductornumexport_fillhash", "callee": "toPlainText", "source_file": "sources/conductornumexport.cpp", "source_location": "L128"}, {"caller_nid": "conductornumexport_fillhash", "callee": "textItem", "source_file": "sources/conductornumexport.cpp", "source_location": "L128"}, {"caller_nid": "conductornumexport_fillhash", "callee": "isEmpty", "source_file": "sources/conductornumexport.cpp", "source_location": "L129"}, {"caller_nid": "conductornumexport_fillhash", "callee": "contains", "source_file": "sources/conductornumexport.cpp", "source_location": "L129"}, {"caller_nid": "conductornumexport_fillhash", "callee": "linkType", "source_file": "sources/conductornumexport.cpp", "source_location": "L135"}, {"caller_nid": "conductornumexport_fillhash", "callee": "parentElement", "source_file": "sources/conductornumexport.cpp", "source_location": "L135"}, {"caller_nid": "conductornumexport_fillhash", "callee": "value", "source_file": "sources/conductornumexport.cpp", "source_location": "L137"}, {"caller_nid": "conductornumexport_fillhash", "callee": "insert", "source_file": "sources/conductornumexport.cpp", "source_location": "L139"}, {"caller_nid": "conductornumexport_fillhash", "callee": "linkType", "source_file": "sources/conductornumexport.cpp", "source_location": "L141"}, {"caller_nid": "conductornumexport_fillhash", "callee": "parentElement", "source_file": "sources/conductornumexport.cpp", "source_location": "L141"}, {"caller_nid": "conductornumexport_fillhash", "callee": "value", "source_file": "sources/conductornumexport.cpp", "source_location": "L143"}, {"caller_nid": "conductornumexport_fillhash", "callee": "insert", "source_file": "sources/conductornumexport.cpp", "source_location": "L145"}]}